accident_manager_service/__init__.py
accident_manager_service/api_client.py
accident_manager_service/configuration.py
accident_manager_service/exceptions.py
accident_manager_service/rest.py
accident_manager_service/api/__init__.py
accident_manager_service/api/accident_api.py
accident_manager_service/api/component_api.py
accident_manager_service/api/event_api.py
accident_manager_service/api/scene_api.py
accident_manager_service/api/time_series_api.py
accident_manager_service/models/__init__.py
accident_manager_service/models/accident_detail_info.py
accident_manager_service/models/accident_detail_input.py
accident_manager_service/models/accident_info.py
accident_manager_service/models/accident_level_enum.py
accident_manager_service/models/accident_type_enum.py
accident_manager_service/models/add_accident_input.py
accident_manager_service/models/add_component_input.py
accident_manager_service/models/add_component_key_input.py
accident_manager_service/models/add_component_value_input.py
accident_manager_service/models/add_event_input.py
accident_manager_service/models/add_scene_input.py
accident_manager_service/models/add_ts_input.py
accident_manager_service/models/business_type_enum.py
accident_manager_service/models/component_detail_info.py
accident_manager_service/models/component_detail_input.py
accident_manager_service/models/component_info.py
accident_manager_service/models/component_key_info.py
accident_manager_service/models/component_value_info.py
accident_manager_service/models/discharge_type_enum.py
accident_manager_service/models/event_detail_info.py
accident_manager_service/models/event_detail_input.py
accident_manager_service/models/event_info.py
accident_manager_service/models/remote_service_error_info.py
accident_manager_service/models/remote_service_error_response.py
accident_manager_service/models/remote_service_validation_error_info.py
accident_manager_service/models/scene_detail_info.py
accident_manager_service/models/scene_detail_input.py
domain_paas_sdk_python-1.0.7.dist-info/LICENSE
domain_paas_sdk_python-1.0.7.dist-info/METADATA
domain_paas_sdk_python-1.0.7.dist-info/WHEEL
domain_paas_sdk_python-1.0.7.dist-info/top_level.txt
domain_paas_sdk_python-1.0.7.dist-info/RECORD
