Metadata-Version: 2.1
Name: domain-paas-sdk-python
Version: 1.0.7
Summary: This template should help get you started developing with python
Home-page: UNKNOWN
Author: dhi
Author-email: wafe@dhigroup.com
License: MIT
Keywords: sdk,python,domain-paas
Platform: UNKNOWN
Requires-Dist: urllib3 (>=1.15)
Requires-Dist: six (>=1.10)
Requires-Dist: certifi
Requires-Dist: python-dateutil
